boltwood/__init__.py
boltwood/base.py
boltwood/base_conditions.py
boltwood/base_safety.py
boltwood/commands.py
boltwood/conditions.py
boltwood/py.typed
boltwood/responses.py
boltwood/safety.py
boltwood/status.py
boltwood/utils.py
boltwood/version.py
boltwood-0.2.0.dist-info/METADATA
boltwood-0.2.0.dist-info/WHEEL
boltwood-0.2.0.dist-info/licenses/LICENSE
boltwood-0.2.0.dist-info/RECORD
