Metadata-Version: 2.4
Name: boltwood
Version: 0.2.0
Summary: A hypermodern, type-safe, zero-dependency python library for the Boltwood II & III cloud sensors.
Project-URL: Source, https://github.com/michealroberts/boltwood
Project-URL: Issues, https://github.com/michealroberts/boltwood/issues
Project-URL: PullRequests, https://github.com/michealroberts/boltwood/pulls
Project-URL: Discussions, https://github.com/michealroberts/boltwood/discussions
Author-email: michealroberts <michael@observerly.com>
Maintainer-email: Michael Roberts <michael@observerly.com>
License: MIT License
License-File: LICENSE
Keywords: boltwood,boltwood-ii,boltwood-iii,boltwood-sensor,cloud-sensor,weather,weather-monitoring,weather-sensor,weather-station
Classifier: Development Status :: 3 - Alpha
Classifier: Intended Audience :: Developers
Classifier: License :: OSI Approved :: MIT License
Classifier: Programming Language :: Python :: 3.13
Requires-Python: >=3.13
Requires-Dist: celerity>=0.31.0
Requires-Dist: pydantic>=2.11.4
Requires-Dist: samps>=0.1.0
